{
	"name": "ds_stores_clean",
	"properties": {
		"linkedServiceName": {
			"referenceName": "ls_storage_connection",
			"type": "LinkedServiceReference"
		},
		"annotations": [],
		"type": "DelimitedText",
		"typeProperties": {
			"location": {
				"type": "AzureBlobStorageLocation",
				"fileName": "ds_stores_clean.csv",
				"folderPath": "Stores",
				"container": "clean"
			},
			"columnDelimiter": ",",
			"escapeChar": "\\",
			"firstRowAsHeader": true,
			"quoteChar": "\""
		},
		"schema": [
			{
				"name": "StoreKey",
				"type": "String"
			},
			{
				"name": "Country",
				"type": "String"
			},
			{
				"name": "State",
				"type": "String"
			},
			{
				"name": "Square Meters",
				"type": "String"
			},
			{
				"name": "Open Date",
				"type": "String"
			}
		]
	}
}